<?xml version="1.0" encoding="utf-8" ?><dwsync><file name="slider_01.jpg" server="gnomo.fe.up.pt/public_html/" local="3564938820" remote="3571341523" Dst="-1" /><file name="slider_02.jpg" server="gnomo.fe.up.pt/public_html/" local="3564938838" remote="3571341523" Dst="-1" /><file name="slider_03.jpg" server="gnomo.fe.up.pt/public_html/" local="3564938856" remote="3571341523" Dst="-1" /><file name="slider_04.jpg" server="gnomo.fe.up.pt/public_html/" local="3565369142" remote="3571341523" Dst="-1" /><file name="slider_05.jpg" server="gnomo.fe.up.pt/public_html/" local="3565371964" remote="3571341523" Dst="-1" /><file name="slider_06.jpg" server="gnomo.fe.up.pt/public_html/" local="3565373476" remote="3571341523" Dst="-1" /><file name="slider_07.jpg" server="gnomo.fe.up.pt/public_html/" local="3565371512" remote="3571341524" Dst="-1" /><file name="slider_08.jpg" server="gnomo.fe.up.pt/public_html/" local="3568315338" remote="3571341524" Dst="-1" /><file name="slider_08_h400.jpg" server="gnomo.fe.up.pt/public_html/" local="3568453140" remote="3571341524" Dst="-1" /><file name="slider_09.jpg" server="gnomo.fe.up.pt/public_html/" local="3568316098" remote="3571341524" Dst="-1" /><file name="slider_09_h400.jpg" server="gnomo.fe.up.pt/public_html/" local="3568453244" remote="3571341524" Dst="-1" /><file name="slider_10.jpg" server="gnomo.fe.up.pt/public_html/" local="3568315666" remote="3571341524" Dst="-1" /><file name="slider_10_h400.jpg" server="gnomo.fe.up.pt/public_html/" local="3568453274" remote="3571341525" Dst="-1" /></dwsync>